flask_accepts/__init__.py
flask_accepts/utils.py
flask_accepts/decorators/__init__.py
flask_accepts/decorators/decorators.py
flask_accepts/tests/__init__.py
flask_accepts/tests/fixtures.py
flask_accepts/tests/test_accepts.py
flask_accepts/tests/test_decorators.py
flask_accepts/tests/test_responds.py
flask_accepts/tests/test_utils.py
flask_accepts-1.0.1.dist-info/LICENSE
flask_accepts-1.0.1.dist-info/METADATA
flask_accepts-1.0.1.dist-info/WHEEL
flask_accepts-1.0.1.dist-info/top_level.txt
flask_accepts-1.0.1.dist-info/RECORD
